unibox-0.12.0.dist-info/METADATA
unibox-0.12.0.dist-info/WHEEL
unibox-0.12.0.dist-info/entry_points.txt
unibox-0.12.0.dist-info/licenses/LICENSE
unibox/__init__.py
unibox/__main__.py
unibox/backends/README.md
unibox/backends/__init__.py
unibox/backends/backend_router.py
unibox/backends/base_backend.py
unibox/backends/hf_hybrid_backend.py
unibox/backends/http_backend.py
unibox/backends/local_backend.py
unibox/backends/s3_backend.py
unibox/cli.py
unibox/debug.py
unibox/loaders/README.md
unibox/loaders/__init__.py
unibox/loaders/base_loader.py
unibox/loaders/csv_loader.py
unibox/loaders/hf_dataset_loader.py
unibox/loaders/image_loder.py
unibox/loaders/json_loader.py
unibox/loaders/jsonl_loader.py
unibox/loaders/loader_router.py
unibox/loaders/parquet_loader.py
unibox/loaders/toml_loader.py
unibox/loaders/txt_loader.py
unibox/loaders/yaml_loader.py
unibox/nb_helpers/__init__.py
unibox/nb_helpers/ipython_utils.py
unibox/nb_helpers/uni_peeker.py
unibox/py.typed
unibox/unibox.py
unibox/utils/README.md
unibox/utils/__init__.py
unibox/utils/constants.py
unibox/utils/credentials_manager.py
unibox/utils/df_utils.py
unibox/utils/globals.py
unibox/utils/image_utils.py
unibox/utils/io_utils.py
unibox/utils/llm_api.py
unibox/utils/logger.py
unibox/utils/s3_client.py
unibox/utils/utils.py
unibox-0.12.0.dist-info/RECORD
