Metadata-Version: 2.1
Name: unibox
Version: 0.12.0
Summary: unibox provides unified interface for common file operations
Author-Email: trojblue <trojblue@gmail.com>
License: MIT
Classifier: Development Status :: 4 - Beta
Classifier: Intended Audience :: Developers
Classifier: Programming Language :: Python
Classifier: Programming Language :: Python :: 3
Classifier: Programming Language :: Python :: 3 :: Only
Classifier: Programming Language :: Python :: 3.10
Classifier: Programming Language :: Python :: 3.11
Classifier: Programming Language :: Python :: 3.12
Classifier: Programming Language :: Python :: 3.13
Classifier: Topic :: Documentation
Classifier: Topic :: Software Development
Classifier: Topic :: Utilities
Classifier: Typing :: Typed
Project-URL: Homepage, https://trojblue.github.io/unibox
Project-URL: Documentation, https://trojblue.github.io/unibox
Project-URL: Changelog, https://trojblue.github.io/unibox/changelog
Project-URL: Repository, https://github.com/trojblue/unibox
Project-URL: Issues, https://github.com/trojblue/unibox/issues
Project-URL: Discussions, https://github.com/trojblue/unibox/discussions
Project-URL: Gitter, https://gitter.im/unibox/community
Project-URL: Funding, https://github.com/sponsors/trojblue
Requires-Python: >=3.10
Requires-Dist: boto3>=1.35.91
Requires-Dist: colorama>=0.4.6
Requires-Dist: colorlog>=6.9.0
Requires-Dist: datasets>=3.2.0
Requires-Dist: orjson>=3.10.13
Requires-Dist: pandas[parquet]>=2.2.3
Requires-Dist: pillow>=11.1.0
Requires-Dist: tomli>=2.2.1
Requires-Dist: tomli-w>=1.2.0
Requires-Dist: tqdm>=4.67.1
